{"lastUsed":1725482982066,"path":"C:\/temp\/Projeto xadrez","projectCount":1,"recentFiles":[{"path":"\/chess_system\/src\/application","parentWorkspace":"C:\/temp\/Projeto xadrez","name":"Program.java","lastModified":1725482982072,"locationURI":"file:\/C:\/temp\/Projeto%20xadrez\/chess_system\/src\/application\/Program.java"},{"path":"\/chess_system\/src\/boardgame","parentWorkspace":"C:\/temp\/Projeto xadrez","name":"Piece.java","lastModified":1725482982117,"locationURI":"file:\/C:\/temp\/Projeto%20xadrez\/chess_system\/src\/boardgame\/Piece.java"},{"path":"\/chess_system\/src\/boardgame","parentWorkspace":"C:\/temp\/Projeto xadrez","name":"Board.java","lastModified":1725482982258,"locationURI":"file:\/C:\/temp\/Projeto%20xadrez\/chess_system\/src\/boardgame\/Board.java"},{"path":"\/chess_system\/src\/boardgame","parentWorkspace":"C:\/temp\/Projeto xadrez","name":"Position.java","lastModified":1725482216388,"locationURI":"file:\/C:\/temp\/Projeto%20xadrez\/chess_system\/src\/boardgame\/Position.java"}]}